local_dsa/__init__.py
local_dsa/check_solutions.py
local_dsa/code_storage.py
local_dsa/core.py
local_dsa/database.py
local_dsa/problems.py
local_dsa/question.py
local_dsa-0.1.2.dist-info/METADATA
local_dsa-0.1.2.dist-info/WHEEL
local_dsa-0.1.2.dist-info/top_level.txt
local_dsa-0.1.2.dist-info/RECORD
