Metadata-Version: 2.4
Name: local_dsa
Version: 0.1.2
Summary: A package for solving coding problems with automatic problem fetching and comments injection
Author-email: Gaurav Bhushan Kumar <gaurav.moocs@gmail.com>
License: MIT
Project-URL: Homepage, https://github.com/Gaurav-822/LocalDSA
Project-URL: Bug Tracker, https://github.com/Gaurav-822/LocalDSA/issues
Requires-Python: >=3.7
